alltoml/__init__.py
alltoml/_argv.py
alltoml/_environ.py
alltoml/_file.py
alltoml/_load.py
alltoml/_parse.py
alltoml/py.typed
alltoml-0.0.0.dist-info/LICENSE
alltoml-0.0.0.dist-info/METADATA
alltoml-0.0.0.dist-info/WHEEL
alltoml-0.0.0.dist-info/RECORD
