Metadata-Version: 2.3
Name: alltoml
Version: 0.0.0
Summary: TOML configuration everywhere
Author: Erik Soma
Author-email: stillusingirc@gmail.com
Requires-Python: >=3.12
Classifier: Programming Language :: Python :: 3
Classifier: Programming Language :: Python :: 3.12
Classifier: Programming Language :: Python :: 3.13
Requires-Dist: deep-chainmap (>=0.1.3,<0.2.0)
Requires-Dist: platformdirs (>=4.4.0,<5.0.0)
